<!-- 
	任务调度
-->
<properties>
		<!--
		quartz引擎监听器配置
		-->
	<property name="quartz.config.schedulerlistener">
		<list componentType="bean">
			<property name="DefaultSchedulerlistener" class="org.frameworkset.task.DefaultSchedulerListener"/>
		</list>
	</property>
	<!--
		任务全局监听器配置
		-->
	<property name="quartz.config.globaljoblistener">
		<list componentType="bean">
			
		</list>
		<!-- for cluster -->
		
	</property>
	<!--
		任务监听器配置
		-->
	<property name="quartz.config.joblistener">
		<list componentType="bean">
			<property name="DefaultJobListener" class="org.frameworkset.task.DefaultJobListener"/>
		</list>
		<!-- for cluster -->
		
	</property>
	<!--
		任务全局Trigger监听器配置
		-->
	<property name="quartz.config.globaltriggerlistener">
		<list componentType="bean">
			<!--<property name="GlobleTriggerListener" class="org.frameworkset.task.GlobalTriggerListener"/>-->
		</list>
		<!-- for cluster -->
		
	</property>
	<!--
		任务Trigger监听器配置
		-->
	<property name="quartz.config.triggerlistener">
		<list componentType="bean">
			<property name="DefaultTriggerListener" class="org.frameworkset.task.DefaultTriggerListener"/>
		</list>
		<!-- for cluster -->
		
	</property>
	<!--
		任务日历配置
		AnnualCalendar
		CronCalendar
		DailyCalendar
		HolidayCalendar
		MonthlyCalendar
		WeeklyCalendar
		-->
	<property name="quartz.config.calendar">
		<map>
			<property name="2012year">
				<![CDATA[ 
				//法定节日是以每年为周期的，所以使用AnnualCalendar
				AnnualCalendar holidays = new AnnualCalendar();
				//五一劳动节
				java.util.Calendar laborDay = new GregorianCalendar();
				laborDay.add(java.util.Calendar.MONTH,5);
				laborDay.add(java.util.Calendar.DATE,1);
				holidays.setDayExcluded(laborDay, true); //排除的日期，如果设置为false则为包含
				//国庆节
				java.util.Calendar nationalDay = new GregorianCalendar();
				nationalDay.add(java.util.Calendar.MONTH,10);
				nationalDay.add(java.util.Calendar.DATE,1);
				holidays.setDayExcluded(nationalDay, true);//排除该日期
				return holidays;
					]]>
			</property>
			<!--<property name="2013year" class="org.frameworkset.task.TestCalendarBuilder"/>-->
		</map>
		<!-- for cluster -->
		
	</property>
	<property name="taskconfig" enable="false">
		<list>
			<property name="定时任务执行器" taskid="default"
				class="org.frameworkset.task.DefaultScheduleService" used="true">
				<!--
					可执行的任务项
					属性说明：
					name：任务项名称
					id:任务项标识
					class:具体的任务执行处理程序,实现org.frameworkset.task.Execute接口
					cron_time：	cron格式的时间表达式，用来管理任务执行的生命周期，相关的规则请参照日期管理控件quartz的说明文档
					used 是否使用
					true 加载，缺省值
					false 不加载	  
					子元素说明：
					parameter:设置任务执行的参数，name标识参数名称，value指定参数的值
				-->
				
				<list>
				  <!-- 
					<property name="runDroolsRules" jobid="runDroolsRules"						
						bean-class="com.frameworkset.platform.integralwarning.drools.service.impl.StartupRuleCalculateServiceImpl"
						method="doCalculate"
						cronb_time="0/30 * * * * ?" used="true"
						shouldRecover="false">
						<construction>
							<property value="100" />
						</construction>
					</property>
					
					<property name="runpointsum" jobid="runpointsum"						
						bean-class="com.frameworkset.platform.integralwarning.assistjudge.service.RunPPointSum"
						method="runPointSum"
						cronb_time="0 0 0/1 * * ?" used="true"
						shouldRecover="false">
					</property>
									
					 <property name="runportalPending" jobid="runportalPending"						
						bean-name="portalMonitor"
						method="PendingMonitor"
						cronb_time="0 0/10 * * * ?" used="false"
						shouldRecover="false">
						
					</property>
					 -->	
					<property name="hrMasterDataSync" 
						jobid="hrMasterDataSync"						
						bean-name="hrSyncTask"
						method="syncAllData"
						cronb_time="0 30 9 * * ?" 
						used="true"
						shouldRecover="false">
					</property>
					
				 <property name="browserCounterStatisticDailyJob" jobid="browserCounterStatisticDailyJob"						
						bean-name="browserCounterStatisticDailyJob"
						method="statisticBrowserCounterDailyJob"
						cronb_time="0 0 0am * * ?" used="false"
						shouldRecover="false"
						>
					</property> 
				 <property name="sanylogBrowserCounterStatisticDailyJob" jobid="sanylogBrowserCounterStatisticDailyJob"						
						bean-name="sanylogBrowserCounterStatisticDailyJob"
						method="statisticBrowserCounterDailyJob"
						cronb_time="0 0 0am * * ?" used="false"
						shouldRecover="false"
						>
					</property>
					<property name="sanylogOperCounterStatisticDailyJob" jobid="sanylogOperCounterStatisticDailyJob"						
						bean-name="sanylogOperCounterStatisticDailyJob"
						method="statisticOperCounterDailyJob"
						cronb_time="59 59 23 * * ?" used="false"
						shouldRecover="false"
						>
					</property> 
				</list>
				 
			</property>
			
			
		</list>
	</property>
	
	<property name="hrSyncTask"  factory-bean="hr.ioccontext" factory-method="getBeanObject">
		<construction>
			<property value="masterdata.hrSyncTask" />
		</construction>
	</property>
	<property name="hr.ioccontext" factory-class="org.frameworkset.spi.DefaultApplicationContext" factory-method="getApplicationContext">
		<construction>
			<property value="bboss-masterdata-humanResource.xml" />
		</construction>
	</property>
	
	
	<property name="portalMonitor" factory-bean="webapplicationcontext" factory-method="getBeanObject">
		<construction>
			<property value="appMonitorService" />
		</construction>
	</property>
	<property name="sanylogOperCounterStatisticDailyJob" factory-bean="webapplicationcontext" factory-method="getBeanObject">
		<construction>
			<property value="sanylogOperCounterStatisticDailyTask" />
		</construction>
	</property>
	 <property name="sanylogBrowserCounterStatisticDailyJob" factory-bean="webapplicationcontext" factory-method="getBeanObject">
		<construction>
			<property value="sanylogBrowserCounterStatisticDailyTask" />
		</construction>
	</property>
	
	<property name="browserCounterStatisticDailyJob" factory-bean="webapplicationcontext" factory-method="getBeanObject">
		<construction>
			<property value="browserCounterStatisticDailyTask" />
		</construction>
	</property> 
	
	<property name="webapplicationcontext" factory-class="org.frameworkset.web.servlet.support.WebApplicationContextUtils" factory-method="getWebApplicationContext"/>
</properties>