<?xml version="1.0" encoding="UTF-8"?>
<!DOCTYPE database SYSTEM "http://db.apache.org/torque/dtd/database_3_3.dtd">
<!-- Autogenerated by JDBCToXMLSchema! -->
<database name="bspf">
    <table name="TB_CMS_DOC_KIND">
        <column name="ID" primaryKey="true" required="true" size="22" type="DECIMAL"/>
        <column name="NAME" required="true" size="100" type="VARCHAR"/>
        <column name="PARENT_ID" size="22" type="DECIMAL"/>
        <column name="ORDER_NO" size="22" type="DECIMAL"/>
    </table>
    <table name="TB_CMS_DOC_LEVEL">
        <column name="ID" primaryKey="true" required="true" size="22" type="DECIMAL"/>
        <column name="NAME" required="true" size="100" type="VARCHAR"/>
        <column name="LEVEL_VALUE" required="true" size="22" type="DECIMAL"/>
    </table>
    <table name="TB_CMS_DOC_OPER">
        <column name="ID" primaryKey="true" required="true" size="22" type="DECIMAL"/>
        <column name="NAME" required="true" size="100" type="VARCHAR"/>
    </table>
    <table name="TB_CMS_DOC_STATUS">
        <column name="ID" primaryKey="true" required="true" size="22" type="DECIMAL"/>
        <column name="NAME" required="true" size="20" type="VARCHAR"/>
        <column name="TYPE" required="true" size="22" type="DECIMAL"/>
    </table>
    <table name="TB_CMS_DOC_STATUS_TRANS">
        <column name="ID" primaryKey="true" required="true" size="22" type="DECIMAL"/>
        <column name="SRC_STATUS" required="true" size="22" type="DECIMAL"/>
        <column name="DEST_STATUS" required="true" size="22" type="DECIMAL"/>
        <column name="TRAN_DESC" size="100" type="VARCHAR"/>
        <foreign-key foreignTable="TB_CMS_DOC_STATUS">
            <reference foreign="ID" local="SRC_STATUS"/>
        </foreign-key>
        <foreign-key foreignTable="TB_CMS_DOC_STATUS">
            <reference foreign="ID" local="DEST_STATUS"/>
        </foreign-key>
    </table>
    <table name="TB_CMS_FLOW">
        <column name="ID" primaryKey="true" required="true" size="22" type="DECIMAL"/>
        <column name="NAME" required="true" size="100" type="VARCHAR"/>
    </table>
    <table name="TB_CMS_FLOW_DOC_TRANS">
        <column name="FLOW_ID" size="22" type="DECIMAL"/>
        <column name="TRANSISION_ID" size="22" type="DECIMAL"/>
        <foreign-key foreignTable="TB_CMS_DOC_STATUS_TRANS">
            <reference foreign="ID" local="TRANSISION_ID"/>
        </foreign-key>
        <foreign-key foreignTable="TB_CMS_FLOW">
            <reference foreign="ID" local="FLOW_ID"/>
        </foreign-key>
    </table>
    <table name="TB_SM_INPUTTYPE">
        <column name="INPUT_TYPE_ID" primaryKey="true" required="true"
            size="5" type="DECIMAL"/>
        <column name="INPUT_TYPE_DESC" size="200" type="VARCHAR"/>
        <column name="DATASOURCE_PATH" size="200" type="VARCHAR"/>
        <column name="INPUT_TYPE_NAME" required="true" size="200" type="VARCHAR"/>
        <column name="SCRIPT" size="4000" type="VARCHAR"/>
    </table>
    <table name="TD_CMS_ADDWATERIMAGE">
        <column name="URL" primaryKey="true" required="true" size="150" type="VARCHAR"/>
        <column name="CREATETIME" type="DATE"/>
        <column name="ISBACKUP" size="2" type="VARCHAR"/>
    </table>
    <table name="TD_CMS_CHANNEL">
        <column name="CHANNEL_ID" primaryKey="true" required="true"
            size="10" type="DECIMAL"/>
        <column name="NAME" required="true" size="256" type="VARCHAR"/>
        <column name="DISPLAY_NAME" size="256" type="VARCHAR"/>
        <column name="PARENT_ID" size="10" type="DECIMAL"/>
        <column name="CHNL_PATH" required="true" size="150" type="VARCHAR"/>
        <column name="CREATEUSER" required="true" size="22" type="DECIMAL"/>
        <column name="CREATETIME" required="true" type="DATE"/>
        <column default="0" name="ORDER_NO" required="true" size="5" type="DECIMAL"/>
        <column name="SITE_ID" required="true" size="10" type="DECIMAL"/>
        <column default="0" name="STATUS" required="true" size="1" type="DECIMAL"/>
        <column name="OUTLINE_TPL_ID" size="10" type="DECIMAL"/>
        <column name="DETAIL_TPL_ID" size="10" type="DECIMAL"/>
        <column default="0" name="WORKFLOW" required="true" size="22" type="DECIMAL"/>
        <column default="0" name="CHNL_OUTLINE_DYNAMIC" required="true"
            size="22" type="DECIMAL"/>
        <column default="0" name="DOC_DYNAMIC" required="true" size="22" type="DECIMAL"/>
        <column default="0" name="CHNL_OUTLINE_PROTECT" required="true"
            size="22" type="DECIMAL"/>
        <column default="0" name="DOC_PROTECT" required="true" size="22" type="DECIMAL"/>
        <column default="1" name="PARENT_WORKFLOW" required="true"
            size="1" type="CHAR"/>
        <column default="default.htm" name="PUB_FILE_NAME"
            required="true" size="100" type="VARCHAR"/>
        <column default="0" name="INHERITSITEFIELD" size="1" type="DECIMAL"/>
        <column default="0" name="ISNAVIGATOR" size="1" type="DECIMAL"/>
        <column name="NAVIGATORLEVEL" size="10" type="DECIMAL"/>
        <column name="MOUSEINIMAGE" size="150" type="VARCHAR"/>
        <column name="MOUSEOUTIMAGE" size="150" type="VARCHAR"/>
        <column name="MOUSECLICKIMAGE" size="150" type="VARCHAR"/>
        <column name="MOUSEUPIMAGE" size="150" type="VARCHAR"/>
        <column name="OUTLINEPICTURE" size="255" type="VARCHAR"/>
        <column name="PAGEFLAG" size="1" type="DECIMAL"/>
        <column name="INDEXPAGEPATH" size="200" type="VARCHAR"/>
        <column name="COMMENTSWITCH" size="1" type="DECIMAL"/>
        <column name="COMMENT_TEMPLATE_ID" size="22" type="DECIMAL"/>
        <column name="COMMENTPAGEPATH" size="200" type="VARCHAR"/>
        <column default="0" name="SPECIALFLAG" size="1" type="DECIMAL"/>
		<column default="_self" name="OPENTARGET" size="32" type="VARCHAR"/>
        <!-- 频道评论审核开关：
        0：评论无需审核
        1：评论需要审核
                     如果频道指定了评论不需要审核，那么频道下所有文档都无需审核
                     如果频道指定了评论需要审核，那么频道下所有文档都需审核，除非文档本身设置为不需要审核
         -->
        <column default="0" name="AUDITFLAG" size="1" type="DECIMAL"/>
        <!-- 频道描述字段，可用于频道发布页面：
         -->
        <column name="CHANNEL_DESC" size="4000" type="VARCHAR"/>
        <foreign-key foreignTable="TB_CMS_FLOW">
            <reference foreign="ID" local="WORKFLOW"/>
        </foreign-key>
        <foreign-key foreignTable="TD_CMS_CHANNEL">
            <reference foreign="CHANNEL_ID" local="PARENT_ID"/>
        </foreign-key>
        <foreign-key foreignTable="TD_CMS_TEMPLATE">
            <reference foreign="TEMPLATE_ID" local="OUTLINE_TPL_ID"/>
        </foreign-key>
    </table>
    <table name="TD_CMS_CHANNELFIELD">
        <column name="FIELD_ID" required="true"
            size="10" type="DECIMAL"/>
        <column name="CHANNEL_ID"  required="true"
            size="10" type="DECIMAL"/>
         <column name="field_owner" required="true"
            size="2" type="DECIMAL" default="0"/>    
            
        <foreign-key foreignTable="TD_CMS_EXTFIELD">
            <reference foreign="FIELD_ID" local="FIELD_ID"/>
        </foreign-key>
        
    </table>
    <table name="TD_CMS_CHANNEL_VOTE">
        <column name="CHANNEL_ID" primaryKey="true" required="true"
            size="22" type="DECIMAL"/>
        <column name="VOTE_TITLE_ID" primaryKey="true" required="true"
            size="22" type="DECIMAL"/>
        <foreign-key foreignTable="TD_CMS_CHANNEL">
            <reference foreign="CHANNEL_ID" local="CHANNEL_ID"/>
        </foreign-key>
        <foreign-key foreignTable="TD_CMS_VOTE_TITLE">
            <reference foreign="ID" local="VOTE_TITLE_ID"/>
        </foreign-key>
    </table>
    <table name="TD_CMS_CHNL_REF_DOC">
        <column name="CHNL_ID" primaryKey="true" required="true"
            size="10" type="DECIMAL"/>
        <column name="DOC_ID" primaryKey="true" required="true"
            size="22" type="DECIMAL"/>
        <column name="OP_USER_ID" required="true" size="22" type="DECIMAL"/>
        <column name="OP_TIME" required="true" type="DATE"/>
        <column name="CITETYPE" size="1" type="DECIMAL"/>
        <column name="SITE_ID" size="22" type="DECIMAL"/>
        <foreign-key foreignTable="TD_CMS_CHANNEL">
            <reference foreign="CHANNEL_ID" local="CHNL_ID"/>
        </foreign-key>
    </table>
    <table name="TD_CMS_COLLECT_ANSWER">
        <column name="ANSWER" type="CLOB"/>
        <column name="CID" size="10" type="DECIMAL"/>
        <column name="WHO_IP" size="100" type="VARCHAR"/>
        <column name="WHEN" type="DATE"/>
        <column name="NAME" size="50" type="VARCHAR"/>
        <column name="STATE" size="1" type="DECIMAL"/>
        <column name="OPERATORID" size="50" type="VARCHAR"/>
        <column name="OTIME" type="DATE"/>
        <column name="ANSTIME" type="DATE"/>
        <column name="ANSWER_ID" primaryKey="true" required="true"
            size="10" type="DECIMAL"/>
        <column name="PHONE" size="50" type="VARCHAR"/>
        <column name="EMAIL" size="50" type="VARCHAR"/>
        <column name="ADDRESS" size="100" type="VARCHAR"/>
        <column name="CARD" size="50" type="VARCHAR"/>
        <column name="TITLE" size="100" type="VARCHAR"/>
    </table>
    <table name="TD_CMS_COLLECT_IPCTRL2">
        <column name="ID" primaryKey="true" required="true" size="10" type="DECIMAL"/>
        <column name="TITLE_ID" size="10" type="DECIMAL"/>
        <column name="IP_START" size="100" type="VARCHAR"/>
        <column name="IP_END" size="100" type="VARCHAR"/>
    </table>
    <table name="TD_CMS_COLLECT_TIMECTRL2">
        <column name="ID" primaryKey="true" required="true" size="10" type="DECIMAL"/>
        <column name="TITLE_ID" size="10" type="DECIMAL"/>
        <column name="TIME_START" type="DATE"/>
        <column name="TIME_END" type="DATE"/>
        <foreign-key foreignTable="TD_CMS_COLLECT_TITLE">
            <reference foreign="ID" local="TITLE_ID"/>
        </foreign-key>
    </table>
    <table name="TD_CMS_COLLECT_TITLE">
        <column name="NAME" size="200" type="VARCHAR"/>
        <column name="CONTENT" type="CLOB"/>
        <column name="ID" primaryKey="true" required="true" size="10" type="DECIMAL"/>
        <column name="SITEID" size="10" type="DECIMAL"/>
        <column name="IP_REPEAT" size="1" type="DECIMAL"/>
        <column name="TIME_GAP" size="22" type="DECIMAL"/>
        <column name="FOUNDER_ID" size="22" type="DECIMAL"/>
        <column name="CTIME" type="DATE"/>
        <column name="ISTOP" size="1" type="DECIMAL"/>
        <column name="DEPART" size="50" type="VARCHAR"/>
        <column name="STIME" type="DATE"/>
        <column name="ETIME" type="DATE"/>
        <column name="STATE" size="1" type="DECIMAL"/>
    </table>
    <table name="TD_CMS_CUSTOM_FORM">
        <column name="TARGET_ID" primaryKey="true" required="true"
            size="10" type="DECIMAL"/>
        <column name="TARGET_TYPE" primaryKey="true" required="true"
            size="1" type="CHAR"/>
        <column name="FORM_TYPE" primaryKey="true" required="true"
            size="1" type="CHAR"/>
        <column name="FILE_NAME" required="true" size="1000" type="VARCHAR"/>
        <column name="DESCRIPTION" size="100" type="VARCHAR"/>
    </table>
    <table name="TD_CMS_DBTSEARCH_DETAIL">
        <column name="ID" primaryKey="true" required="true" size="22" type="DECIMAL"/>
        <column name="DB_NAME" required="true" size="50" type="VARCHAR"/>
        <column name="TABLE_NAME" required="true" size="50" type="VARCHAR"/>
        <column name="CONTENT_FIELDS" required="true" size="200" type="VARCHAR"/>
        <column name="TITLE_FIELD" size="40" type="VARCHAR"/>
        <column name="DESCRIPTION_FIELD" size="40" type="VARCHAR"/>
        <column name="KEYWORD_FIELD" size="40" type="VARCHAR"/>
        <column name="PUBLISHTIME_FIELD" size="40" type="VARCHAR"/>
        <column name="ACCESS_URL" size="100" type="VARCHAR"/>
        <column name="WHERES" size="200" type="VARCHAR"/>
        <column name="PRIMARYS" size="200" type="VARCHAR"/>
        <column name="CONTENT_TYPES" size="100" type="VARCHAR"/>
        <column name="CONTENT_PATH" size="100" type="VARCHAR"/>
        <foreign-key foreignTable="TD_CMS_SITE_SEARCH">
            <reference foreign="ID" local="ID"/>
        </foreign-key>
    </table>
    <table name="TD_CMS_DOCCOMMENT_DICT">
        <column name="ID" primaryKey="true" required="true" size="22" type="DECIMAL"/>
        <column name="WORD" required="true" size="50" type="VARCHAR"/>
        <column name="DESCRIPTION" size="200" type="VARCHAR"/>
        <column name="SITEID" required="true" size="10" type="DECIMAL"/>
    </table>
    <table name="TD_CMS_DOCCOM_IMPEACHINFO">
        <column name="ID" primaryKey="true" required="true" size="22" type="DECIMAL"/>
        <column name="COMMENT_ID" required="true" size="22" type="DECIMAL"/>
        <column name="IMPEACHER" required="true" size="50" type="VARCHAR"/>
        <column name="EMAIL" size="30" type="VARCHAR"/>
        <column name="REASON" required="true" size="1" type="DECIMAL"/>
        <column name="DESCRIPTIONINFO" size="200" type="VARCHAR"/>
        <column name="COMTIME" required="true" type="DATE"/>
        <column name="REPLYED" size="1" type="DECIMAL"/>
        <foreign-key foreignTable="TD_CMS_DOC_COMMENT">
            <reference foreign="COMMENT_ID" local="COMMENT_ID"/>
        </foreign-key>
    </table>
    <table name="TD_CMS_DOCSOURCE">
        <column name="SRCNAME" required="true" size="200" type="VARCHAR"/>
        <column name="SRCDESC" size="200" type="VARCHAR"/>
        <column name="SRCLINK" size="200" type="VARCHAR"/>
        <column name="CRUSER" size="5" type="DECIMAL"/>
        <column name="CRTIME" type="DATE"/>
        <column name="DOCSOURCE_ID" primaryKey="true" required="true"
            size="10" type="DECIMAL"/>
    </table>
    <!-- ALTER TABLE SANYGCMP.TD_CMS_DOCUMENT ADD CONSTRAINT TD_CMS_DOCUMENT_fk7 FOREIGN KEY (DOC_CLASS) REFERENCES SANYGCMP.TD_CMS_DOCUMENT_CLASS (CLASS_NAME) -->
    <table name="TD_CMS_DOCUMENT">
        <column name="DOCUMENT_ID" primaryKey="true" required="true"
            size="22" type="DECIMAL"/>
        <column name="TITLE" required="true" size="400" type="VARCHAR"/>
        <column name="SUBTITLE" required="true" size="300" type="VARCHAR"/>
        <column name="AUTHOR" size="255" type="VARCHAR"/>
        <column name="CONTENT" type="CLOB"/>
        <column name="CHANNEL_ID" required="true" size="10" type="DECIMAL"/>
        <column name="STATUS" required="true" size="22" type="DECIMAL"/>
        <column name="KEYWORDS" size="500" type="VARCHAR"/>
        <column name="DOCABSTRACT" size="2000" type="VARCHAR"/>
        <column name="DOCTYPE" required="true" size="22" type="DECIMAL"/>
        <column name="DOCWTIME" required="true" type="DATE"/>
        <column name="TITLECOLOR" size="7" type="VARCHAR"/>
        <column name="CREATETIME" required="true" type="DATE"/>
        <column name="CREATEUSER" required="true" size="10" type="DECIMAL"/>
        <column name="DOCSOURCE_ID" required="true" size="10" type="DECIMAL"/>
        <column name="DETAILTEMPLATE_ID" size="10" type="DECIMAL"/>
        <column name="LINKTARGET" size="100" type="VARCHAR"/>
        <column name="FLOW_ID" size="22" type="DECIMAL"/>
        <column name="DOC_LEVEL" size="22" type="DECIMAL"/>
        <column name="DOC_KIND" size="22" type="DECIMAL"/>
        <column name="DOC_CLASS" size="50" type="VARCHAR"/>
        <column default="1" name="PARENT_DETAIL_TPL" required="true"
            size="1" type="CHAR"/>
        <column default="0" name="ISDELETED" size="5" type="DECIMAL"/>
        <column name="AUDITTIME" type="DATE"/>
        <column name="PUBLISHTIME" type="DATE"/>
        <column name="GUIDANGTIME" type="DATE"/>
        <column name="RECYCLETIME" type="DATE"/>
        <column name="GUIDANGMAN" size="10" type="DECIMAL"/>
        <column name="RECYCLEMAN" size="10" type="DECIMAL"/>
        <column default="1" name="VERSION" size="4" type="DECIMAL"/>
        <column name="PIC_PATH" size="200" type="VARCHAR"/>
        <column name="MEDIAPATH" size="200" type="VARCHAR"/>
        <column name="PUBLISHFILENAME" size="100" type="VARCHAR"/>
        <column name="COMMENT_TEMPLATE_ID" size="22" type="DECIMAL"/>
        <column name="COMMENTSWITCH" size="1" type="DECIMAL"/>
        <column name="SECONDTITLE" size="300" type="VARCHAR"/>
        <column default="0" name="ISNEW" size="1" type="DECIMAL"/>
        <column name="NEWPIC_PATH" size="200" type="VARCHAR"/>
        <column name="ORDERTIME" type="DATE"/>
        <column name="FILECONTENT" type="BLOB"/>
        <column default="9999" name="SEQ" size="22" type="DECIMAL"/>
        <column name="EXT_CLASS" size="300" type="VARCHAR"/>
        <column name="EXT_ORG" size="200" type="VARCHAR"/>
        <column name="EXT_WH" size="100" type="VARCHAR"/>
        <column name="EXT_INDEX" size="50" type="VARCHAR"/>
        <column name="EXT_DJH" size="100" type="VARCHAR"/>
        <column default="0" name="COUNT" size="22" type="DECIMAL"/>
        <!-- 文档评论审核开关：
        0：评论无需审核
        1：评论需要审核
                       如果频道已经关闭审核功能，则文档审核也会关闭，反之，以文档标志为准                     
        
         -->
        <column default="0" name="AUDITFLAG" size="1" type="DECIMAL"/>
        <foreign-key foreignTable="TD_CMS_DOCSOURCE">
            <reference foreign="DOCSOURCE_ID" local="DOCSOURCE_ID"/>
        </foreign-key>
        <foreign-key foreignTable="TB_CMS_FLOW">
            <reference foreign="ID" local="FLOW_ID"/>
        </foreign-key>
        <foreign-key foreignTable="TB_CMS_DOC_STATUS">
            <reference foreign="ID" local="STATUS"/>
        </foreign-key>
        <foreign-key foreignTable="TB_CMS_DOC_KIND">
            <reference foreign="ID" local="DOC_KIND"/>
        </foreign-key>
        <foreign-key foreignTable="TD_CMS_CHANNEL">
            <reference foreign="CHANNEL_ID" local="CHANNEL_ID"/>
        </foreign-key>
        <foreign-key foreignTable="TB_CMS_DOC_LEVEL">
            <reference foreign="ID" local="DOC_LEVEL"/>
        </foreign-key>
    </table>
    <table name="TD_CMS_DOCUMENT_TEMP">
        <column name="DOCUMENT_ID" required="true" size="22" type="DECIMAL"/>
        <column name="TITLE" required="true" size="400" type="VARCHAR"/>
        <column name="SUBTITLE" required="true" size="300" type="VARCHAR"/>
        <column name="AUTHOR" size="255" type="VARCHAR"/>
        <column name="CONTENT" type="CLOB"/>
        <column name="CHANNEL_ID" required="true" size="10" type="DECIMAL"/>
        <column name="STATUS" required="true" size="22" type="DECIMAL"/>
        <column name="KEYWORDS" size="500" type="VARCHAR"/>
        <column name="DOCABSTRACT" size="2000" type="VARCHAR"/>
        <column name="DOCTYPE" required="true" size="22" type="DECIMAL"/>
        <column name="DOCWTIME" required="true" type="DATE"/>
        <column name="TITLECOLOR" size="7" type="VARCHAR"/>
        <column name="CREATETIME" required="true" type="DATE"/>
        <column name="CREATEUSER" required="true" size="10" type="DECIMAL"/>
        <column name="DOCSOURCE_ID" required="true" size="10" type="DECIMAL"/>
        <column name="DETAILTEMPLATE_ID" size="10" type="DECIMAL"/>
        <column name="LINKTARGET" size="100" type="VARCHAR"/>
        <column name="FLOW_ID" required="true" size="22" type="DECIMAL"/>
        <column name="DOC_LEVEL" size="22" type="DECIMAL"/>
        <column name="DOC_KIND" size="22" type="DECIMAL"/>
        <column name="PARENT_DETAIL_TPL" required="true" size="1" type="CHAR"/>
        <column name="ISDELETED" size="5" type="DECIMAL"/>
        <column name="AUDITTIME" type="DATE"/>
        <column name="PUBLISHTIME" type="DATE"/>
        <column name="GUIDANGTIME" type="DATE"/>
        <column name="RECYCLETIME" type="DATE"/>
        <column name="GUIDANGMAN" size="10" type="DECIMAL"/>
        <column name="RECYCLEMAN" size="10" type="DECIMAL"/>
        <column name="VERSION" size="4" type="DECIMAL"/>
    </table>
    <table name="TD_CMS_DOC_AGGREGATION">
        <column name="AGGR_DOC_ID" primaryKey="true" required="true"
            size="22" type="DECIMAL"/>
        <column name="SEQ" primaryKey="true" required="true" size="22" type="DECIMAL"/>
        <column name="ID_BY_AGGR" required="true" size="22" type="DECIMAL"/>
        <column name="TITLE" required="true" size="100" type="VARCHAR"/>
        <column name="TYPE" required="true" size="1" type="CHAR"/>
        <foreign-key foreignTable="TD_CMS_DOCUMENT">
            <reference foreign="DOCUMENT_ID" local="AGGR_DOC_ID"/>
        </foreign-key>
    </table>
    <table name="TD_CMS_DOC_ARRANGE">
        <column name="DOCUMENT_ID" primaryKey="true" required="true"
            size="22" type="DECIMAL"/>
        <column name="START_TIME" required="true" size="100" type="VARCHAR"/>
        <column name="END_TIME" required="true" size="100" type="VARCHAR"/>
        <column name="ORDER_NO" required="true" size="22" type="DECIMAL"/>
        <column name="OP_USER" required="true" size="22" type="DECIMAL"/>
        <column name="OP_TIME" required="true" type="DATE"/>
        <foreign-key foreignTable="TD_CMS_DOCUMENT">
            <reference foreign="DOCUMENT_ID" local="DOCUMENT_ID"/>
        </foreign-key>
    </table>
    <table name="TD_CMS_DOC_ATTACH">
        <column name="ID" primaryKey="true" required="true" size="10" type="DECIMAL"/>
        <column name="DOCUMENT_ID" required="true" size="10" type="DECIMAL"/>
        <column name="URL" required="true" size="500" type="VARCHAR"/>
        <column name="TYPE" required="true" size="2" type="DECIMAL"/>
        <column name="DESCRIPTION" size="500" type="VARCHAR"/>
        <column name="ORIGINAL_FILENAME" required="true" size="500" type="VARCHAR"/>
        <column default="1" name="VALID" required="true" size="1" type="CHAR"/>
        <foreign-key foreignTable="TD_CMS_DOCUMENT">
            <reference foreign="DOCUMENT_ID" local="DOCUMENT_ID"/>
        </foreign-key>
    </table>
    <table name="TD_CMS_DOC_COMMENT">
        <column name="COMMENT_ID" primaryKey="true" required="true"
            size="10" type="DECIMAL"/>
        <column name="DOC_ID" size="10" type="DECIMAL"/>
        <column name="DOC_COMMENT" required="true" type="CLOB"/>
        <column name="USER_NAME" size="100" type="VARCHAR"/>
        <column name="COMTIME" type="DATE"/>
        <column name="USER_IP" size="100" type="VARCHAR"/>
        <column name="SRC_COMMENT_ID" size="10" type="DECIMAL"/>
        <column name="STATUS" size="22" type="DECIMAL"/>
        <foreign-key foreignTable="TD_CMS_DOCUMENT">
            <reference foreign="DOCUMENT_ID" local="DOC_ID"/>
        </foreign-key>
        <foreign-key foreignTable="TD_CMS_DOC_COMMENT">
            <reference foreign="COMMENT_ID" local="SRC_COMMENT_ID"/>
        </foreign-key>
    </table>
    <table name="TD_CMS_DOC_DIST_MANNER">
        <column name="DOCUMENT_ID" primaryKey="true" required="true"
            size="22" type="DECIMAL"/>
        <column name="DIST_MANNER_ID" primaryKey="true" required="true"
            size="22" type="DECIMAL"/>
        <foreign-key foreignTable="TD_CMS_DOCUMENT">
            <reference foreign="DOCUMENT_ID" local="DOCUMENT_ID"/>
        </foreign-key>
    </table>
    <table name="TD_CMS_DOC_PUBLISHING">
        <column name="DOCUMENT_ID" primaryKey="true" required="true"
            size="22" type="DECIMAL"/>
        <column name="OLD_STATUS" required="true" size="10" type="DECIMAL"/>
        <column name="PUBLISHER" size="100" type="VARCHAR"/>
        <column name="PUB_START_TIME" type="DATE"/>
        <foreign-key foreignTable="TD_CMS_DOCUMENT">
            <reference foreign="DOCUMENT_ID" local="DOCUMENT_ID"/>
        </foreign-key>
    </table>
    <table name="TD_CMS_DOC_RELATED">
        <column name="DOC_ID" primaryKey="true" required="true"
            size="22" type="DECIMAL"/>
        <column name="RELATED_DOC_ID" primaryKey="true" required="true"
            size="22" type="DECIMAL"/>
        <column name="OP_USER_ID" required="true" size="22" type="DECIMAL"/>
        <column name="OP_TIME" required="true" type="DATE"/>
        <foreign-key foreignTable="TD_CMS_DOCUMENT">
            <reference foreign="DOCUMENT_ID" local="RELATED_DOC_ID"/>
        </foreign-key>
        <foreign-key foreignTable="TD_CMS_DOCUMENT">
            <reference foreign="DOCUMENT_ID" local="DOC_ID"/>
        </foreign-key>
    </table>
    <table name="TD_CMS_DOC_TASK">
        <column name="TASK_ID" primaryKey="true" required="true"
            size="10" type="DECIMAL"/>
        <column name="PRE_TASK_ID" size="10" type="DECIMAL"/>
        <column name="DOCUMENT_ID" required="true" size="22" type="DECIMAL"/>
        <column name="PRE_STATUS" size="22" type="DECIMAL"/>
        <column name="SUBMIT_ID" required="true" size="22" type="DECIMAL"/>
        <column name="SUBMIT_TIME" required="true" type="DATE"/>
        <foreign-key foreignTable="TD_CMS_DOCUMENT">
            <reference foreign="DOCUMENT_ID" local="DOCUMENT_ID"/>
        </foreign-key>
        <foreign-key foreignTable="TB_CMS_DOC_STATUS">
            <reference foreign="ID" local="PRE_STATUS"/>
        </foreign-key>
    </table>
    <table name="TD_CMS_DOC_TASK_DETAIL">
        <column name="TASK_ID" primaryKey="true" required="true"
            size="10" type="DECIMAL"/>
        <column name="PERFORMER" primaryKey="true" required="true"
            size="22" type="DECIMAL"/>
        <column name="AFTER_STATUS" size="22" type="DECIMAL"/>
        <column default="1" name="VALID" size="22" type="DECIMAL"/>
        <column name="COMPLETE_TIME" type="DATE"/>
        <column name="OPINION" size="500" type="VARCHAR"/>
        <foreign-key foreignTable="TB_CMS_DOC_STATUS">
            <reference foreign="ID" local="AFTER_STATUS"/>
        </foreign-key>
    </table>
    <table name="TD_CMS_DOC_TEMPLATE">
        <column name="ID" primaryKey="true" required="true" size="10" type="DECIMAL"/>
        <column name="TPLNAME" required="true" size="50" type="VARCHAR"/>
        <column name="TPLCODE" required="true" type="CLOB"/>
        <column name="CHANNEL_ID" required="true" size="10" type="DECIMAL"/>
        <column name="CREATOR" required="true" size="10" type="DECIMAL"/>
        <column name="DESCRIPTION" size="200" type="VARCHAR"/>
        <column name="CREATTIME" required="true" type="DATE"/>
        <foreign-key foreignTable="TD_CMS_CHANNEL">
            <reference foreign="CHANNEL_ID" local="CHANNEL_ID"/>
        </foreign-key>
    </table>
    <table name="TD_CMS_DOC_VER">
        <column name="DOCUMENT_ID" primaryKey="true" required="true"
            size="22" type="DECIMAL"/>
        <column name="VERSION" primaryKey="true" required="true"
            size="22" type="DECIMAL"/>
        <column name="TITLE" required="true" size="400" type="VARCHAR"/>
        <column name="SUBTITLE" required="true" size="300" type="VARCHAR"/>
        <column name="AUTHOR" size="255" type="VARCHAR"/>
        <column name="CONTENT" type="CLOB"/>
        <column name="CHANNEL_ID" required="true" size="10" type="DECIMAL"/>
        <column name="KEYWORDS" size="500" type="VARCHAR"/>
        <column name="DOCABSTRACT" size="2000" type="VARCHAR"/>
        <column name="DOCTYPE" required="true" size="22" type="DECIMAL"/>
        <column name="DOCWTIME" required="true" type="DATE"/>
        <column name="TITLECOLOR" size="7" type="VARCHAR"/>
        <column name="DOCSOURCE_ID" required="true" size="10" type="DECIMAL"/>
        <column name="DETAILTEMPLATE_ID" size="10" type="DECIMAL"/>
        <column name="LINKTARGET" size="100" type="VARCHAR"/>
        <column name="FLOW_ID" required="true" size="22" type="DECIMAL"/>
        <column name="DOC_LEVEL" size="22" type="DECIMAL"/>
        <column name="DOC_KIND" size="22" type="DECIMAL"/>
        <column name="PARENT_DETAIL_TPL" required="true" size="1" type="CHAR"/>
        <column name="OP_USER" required="true" size="22" type="DECIMAL"/>
        <column name="OP_TIME" required="true" type="DATE"/>
        <column name="LABEL" size="100" type="VARCHAR"/>
        <column name="VERSIONDESCRIPTION" size="100" type="VARCHAR"/>
        <column name="PIC_PATH" size="100" type="VARCHAR"/>
        <column name="MEDIAPATH" size="200" type="VARCHAR"/>
        <column name="PUBLISHFILENAME" size="50" type="VARCHAR"/>
        <column name="SECONDTITLE" size="300" type="VARCHAR"/>
        <column name="ISNEW" size="1" type="DECIMAL"/>
        <column name="NEWPIC_PATH" size="200" type="VARCHAR"/>
        <foreign-key foreignTable="TD_CMS_DOCUMENT">
            <reference foreign="DOCUMENT_ID" local="DOCUMENT_ID"/>
        </foreign-key>
    </table>
    <table name="TD_CMS_DOC_VER_ATTACH">
        <column name="DOCUMENT_ID" primaryKey="true" required="true"
            size="22" type="DECIMAL"/>
        <column name="VERSION" primaryKey="true" required="true"
            size="22" type="DECIMAL"/>
        <column name="ATTACH_ID" primaryKey="true" required="true"
            size="10" type="DECIMAL"/>
        <foreign-key foreignTable="TD_CMS_DOC_ATTACH">
            <reference foreign="ID" local="ATTACH_ID"/>
        </foreign-key>
        <foreign-key foreignTable="TD_CMS_DOC_VER">
            <reference foreign="DOCUMENT_ID" local="DOCUMENT_ID"/>
            <reference foreign="VERSION" local="VERSION"/>
        </foreign-key>
    </table>
    <table name="TD_CMS_EXTFIELD">
        <column name="FIELD_ID" primaryKey="true" required="true"
            size="10" type="DECIMAL"/>
        <column name="FIELDNAME" required="true" size="100" type="VARCHAR"/>
        <column name="FIELDLABEL" required="true" size="100" type="VARCHAR"/>
        <column name="FIELDDESC" size="500" type="VARCHAR"/>
        <column name="FIELDTYPE" size="100" type="VARCHAR"/>
        <column name="MAXLEN" size="4" type="DECIMAL"/>
        <column name="INPUTTYPE" size="10" type="DECIMAL"/>
    </table>
    <table name="TD_CMS_EXTFIELDVALUE">
        <column name="FIELD_ID" primaryKey="true" required="true"
            size="10" type="DECIMAL"/>
        <column name="DOCUMENT_ID" primaryKey="true" required="true"
            size="22" type="DECIMAL"/>
        <column name="FIELDVALUE" size="4000" type="VARCHAR"/>
        <column name="NUMBERVALUE" size="10" type="DECIMAL"/>
        <column name="CLOBVALUE" type="CLOB"/>
        <column name="DATEVALUE" type="DATE"/>
        <foreign-key foreignTable="TD_CMS_EXTFIELD">
            <reference foreign="FIELD_ID" local="FIELD_ID"/>
        </foreign-key>
        <foreign-key foreignTable="TD_CMS_DOCUMENT">
            <reference foreign="DOCUMENT_ID" local="DOCUMENT_ID"/>
        </foreign-key>
    </table>
    <table name="TD_CMS_EXTVALUESCOPE">
        <column name="FIELD_ID" size="10" type="DECIMAL"/>
        <column name="VALUE" size="100" type="VARCHAR"/>
        <column name="ID" primaryKey="true" required="true" size="10" type="DECIMAL"/>
        <column name="DESCRIPTION" size="100" type="VARCHAR"/>
        <column name="MINVALUE" size="10" type="DECIMAL"/>
        <column name="MAXVALUE" size="10" type="DECIMAL"/>
        <foreign-key foreignTable="TD_CMS_EXTFIELD">
            <reference foreign="FIELD_ID" local="FIELD_ID"/>
        </foreign-key>
    </table>
    <table name="TD_CMS_FILE_CHANGE_LOG">
        <column name="SITE_ID" required="true" size="40" type="VARCHAR"/>
        <column name="URI" required="true" size="510" type="VARCHAR"/>
        <column default="1.0" name="VERSION" required="true" size="22" type="DECIMAL"/>
        <column name="USER_ID" required="true" size="40" type="VARCHAR"/>
        <column name="CHANGE_TIME" required="true" type="DATE"/>
        <column name="BAK_FILE_NAME" size="510" type="VARCHAR"/>
        <column name="CHANGE_REMARK" size="510" type="VARCHAR"/>
    </table>
    <table name="TD_CMS_FILE_STATUS">
        <column name="SITE_ID" primaryKey="true" required="true"
            size="40" type="VARCHAR"/>
        <column name="URI" primaryKey="true" required="true" size="200" type="VARCHAR"/>
        <column name="VERSION" scale="1" size="6" type="DECIMAL"/>
        <column name="CHECKOUT_USER" size="40" type="VARCHAR"/>
        <column name="CHECKOUT_TIME" type="DATE"/>
    </table>
    <table name="TD_CMS_MAILSERVERINFO">
        <column name="ID" primaryKey="true" required="true" size="22" type="DECIMAL"/>
        <column name="SMTP_SERVER" size="200" type="VARCHAR"/>
        <column name="MAIL_SENDER" size="200" type="VARCHAR"/>
        <column name="MAIL_SENDERNAME" size="200" type="VARCHAR"/>
        <column name="MAIL_DESC" size="500" type="VARCHAR"/>
        <column name="SERVER_NAME" size="100" type="VARCHAR"/>
        <column name="MAIL_DOMAIN" size="500" type="VARCHAR"/>
        <column name="MAIL_USERNAME" size="100" type="VARCHAR"/>
        <column name="MAIL_PASSWORD" size="100" type="VARCHAR"/>
        <column default="25" name="SMTP_PORT" size="100" type="VARCHAR"/>
    </table>
    <table name="TD_CMS_PUBOBJECT_RELATION">
        <column name="PUBLISHOBJECT" primaryKey="true" required="true"
            size="200" type="VARCHAR"/>
        <column name="REFERENCEOBJECT" primaryKey="true" required="true"
            size="200" type="VARCHAR"/>
        <column name="PUBLISHTYPE" primaryKey="true" required="true"
            size="22" type="DECIMAL"/>
        <column name="PUBLISH_SITE" primaryKey="true" required="true"
            size="200" type="VARCHAR"/>
        <column name="REFERENCETYPE" primaryKey="true" required="true"
            size="22" type="DECIMAL"/>
        <column name="REFERENCE_SITE" primaryKey="true" required="true"
            size="100" type="VARCHAR"/>
        <column name="COUNTER" size="22" type="DECIMAL"/>
    </table>
    <table name="TD_CMS_SITE">
        <column name="SITE_ID" primaryKey="true" required="true"
            size="10" type="DECIMAL"/>
        <column name="NAME" required="true" size="100" type="VARCHAR"/>
        <column name="SECOND_NAME" size="100" type="VARCHAR"/>
        <column name="MAINSITE_ID" size="10" type="DECIMAL"/>
        <column name="SITEDESC" size="150" type="VARCHAR"/>
        <column name="DBNAME" size="40" type="VARCHAR"/>
        <column name="SITEDIR" required="true" size="500" type="VARCHAR"/>
        <column name="STATUS" size="1" type="DECIMAL"/>
        <column name="FTPIP" size="17" type="VARCHAR"/>
        <column name="FTPPORT" size="4" type="VARCHAR"/>
        <column name="FTPUSER" size="20" type="VARCHAR"/>
        <column name="FTPPASSWORD" size="20" type="VARCHAR"/>
        <column name="FTPFOLDER" size="20" type="VARCHAR"/>
        <column name="WEBHTTP" size="100" type="VARCHAR"/>
        <column name="SITEORDER" size="5" type="DECIMAL"/>
        <column name="CREATETIME" required="true" type="DATE"/>
        <column name="CREATEUSER" required="true" size="22" type="DECIMAL"/>
        <column name="PUBLISHDESTINATION" size="1" type="DECIMAL"/>
        <column name="INDEXFILENAME" size="50" type="VARCHAR"/>
        <column name="INDEXTEMPLATE_ID" size="10" type="DECIMAL"/>
        <column name="FLOW_ID" size="22" type="DECIMAL"/>
        <column default="1" name="PARENT_WORKFLOW" required="true"
            size="1" type="CHAR"/>
        <column name="LOCALPUBLISHPATH" size="510" type="VARCHAR"/>
        <column name="DISTRIBUTEMANNERS" size="50" type="VARCHAR"/>
        <column name="SITEENCODEING" size="100" type="VARCHAR"/>
        <foreign-key foreignTable="TD_CMS_SITE">
            <reference foreign="SITE_ID" local="MAINSITE_ID"/>
        </foreign-key>
        <foreign-key foreignTable="TB_CMS_FLOW">
            <reference foreign="ID" local="FLOW_ID"/>
        </foreign-key>
    </table>
    <table name="TD_CMS_SITEAPPS">
        <column name="SITE_ID" primaryKey="true" required="true"
            size="22" type="DECIMAL"/>
        <column name="APP_ID" primaryKey="true" required="true"
            size="200" type="VARCHAR"/>
        <column name="APP_PATH" size="500" type="VARCHAR"/>
        <foreign-key foreignTable="TD_CMS_SITE">
            <reference foreign="SITE_ID" local="SITE_ID"/>
        </foreign-key>
    </table>
    <table name="TD_CMS_SITEFIELD">
        <column name="FILE_ID" primaryKey="true" required="true"
            size="10" type="DECIMAL"/>
        <column name="SITE_ID" primaryKey="true" required="true"
            size="10" type="DECIMAL"/>
        <foreign-key foreignTable="TD_CMS_SITE">
            <reference foreign="SITE_ID" local="SITE_ID"/>
        </foreign-key>
        <foreign-key foreignTable="TD_CMS_EXTFIELD">
            <reference foreign="FIELD_ID" local="FILE_ID"/>
        </foreign-key>
    </table>
    <table name="TD_CMS_SITEUSER">
        <column name="SITE_ID" primaryKey="true" required="true"
            size="22" type="DECIMAL"/>
        <column name="USER_ID" primaryKey="true" required="true"
            size="22" type="DECIMAL"/>
        <foreign-key foreignTable="TD_CMS_SITE">
            <reference foreign="SITE_ID" local="SITE_ID"/>
        </foreign-key>
    </table>
    <table name="TD_CMS_SITE_SEARCH">
        <column name="SITE_ID" required="true" size="10" type="DECIMAL"/>
        <column name="CHNL_OR_DOMAIN" size="100" type="VARCHAR"/>
        <column default="0" name="LEVER" size="1" type="DECIMAL"/>
        <column default="1" name="DAY" size="2" type="DECIMAL"/>
        <column default="0" name="TIME" size="2" type="DECIMAL"/>
        <column default="0" name="SEARCH_TYPE" required="true" size="1" type="DECIMAL"/>
        <column name="START_URL" size="100" type="VARCHAR"/>
        <column name="ID" primaryKey="true" required="true" size="22" type="DECIMAL"/>
        <column name="NAME" required="true" size="30" type="VARCHAR"/>
        <column name="SITE_IDS" size="100" type="VARCHAR"/>
    </table>
    <table name="TD_CMS_SITE_TPL">
        <column name="SITE_ID" primaryKey="true" required="true"
            size="10" type="DECIMAL"/>
        <column name="TEMPLATE_ID" primaryKey="true" required="true"
            size="10" type="DECIMAL"/>
        <foreign-key foreignTable="TD_CMS_SITE">
            <reference foreign="SITE_ID" local="SITE_ID"/>
        </foreign-key>
        <foreign-key foreignTable="TD_CMS_TEMPLATE">
            <reference foreign="TEMPLATE_ID" local="TEMPLATE_ID"/>
        </foreign-key>
    </table>
    <table name="TD_CMS_TEMPLATE">
        <column name="TEMPLATE_ID" primaryKey="true" required="true"
            size="10" type="DECIMAL"/>
        <column name="NAME" required="true" size="255" type="VARCHAR"/>
        <column name="DESCRIPTION" size="255" type="VARCHAR"/>
        <column name="HEADER" required="true" size="3000" type="VARCHAR"/>
        <column name="TEXT" type="CLOB"/>
        <column name="TYPE" required="true" size="5" type="DECIMAL"/>
        <column name="CREATEUSER" required="true" size="22" type="DECIMAL"/>
        <column name="CREATETIME" required="true" type="DATE"/>
        <column default="0" name="INC_PUB_FLAG" required="true" size="1" type="CHAR"/>
        <column default="0" name="PERSISTTYPE" size="5" type="DECIMAL"/>
        <column name="TEMPLATEFILENAME" size="100" type="VARCHAR"/>
        <column name="TEMPLATEPATH" size="255" type="VARCHAR"/>
        <column default="-1" name="TEMPLATE_STYLE" size="5" type="DECIMAL"/>
    </table>
    <table name="TD_CMS_TEMPLATE_STYLE">
        <column name="STYLE_ID" primaryKey="true" required="true"
            size="5" type="DECIMAL"/>
        <column name="STYLE_NAME" size="200" type="VARCHAR"/>
        <column name="STYLE_DESC" size="500" type="VARCHAR"/>
        <column name="STYLE_ORDER" size="5" type="DECIMAL"/>
    </table>
    <table name="TD_CMS_TMPL_EXPORT">
        <column name="TMPLNAME" primaryKey="true" required="true"
            size="50" type="VARCHAR"/>
        <column name="TMPLDESC" size="400" type="VARCHAR"/>
        <column name="EXPORTDATE" type="DATE"/>
        <column name="EXPORTERID" size="22" type="DECIMAL"/>
        <column name="FLAG" size="2" type="VARCHAR"/>
        <column name="SITEID" size="22" type="DECIMAL"/>
    </table>
    <table name="TD_CMS_VOTE_ANSWER">
        <column name="ANSER_ID" primaryKey="true" required="true"
            size="10" type="DECIMAL"/>
        <column name="QID" size="10" type="DECIMAL"/>
        <column default="0" name="TYPE" size="1" type="DECIMAL"/>
        <column name="ITEM_ID" size="22" type="DECIMAL"/>
        <column name="WHO_IP" size="100" type="VARCHAR"/>
        <column name="WHEN" type="DATE"/>
        <column name="ISBIGTITLE" size="1" type="DECIMAL"/>
        <column default="0" name="STATE" size="1" type="DECIMAL"/>
        <column name="ANSWER" type="CLOB"/>
        <column name="TITLE_ID" size="80" type="VARCHAR"/>
        <column name="USER_ID" size="100" type="VARCHAR"/>
        <foreign-key foreignTable="TD_CMS_VOTE_QUESTIONS">
            <reference foreign="ID" local="QID"/>
        </foreign-key>
    </table>
    <table name="TD_CMS_VOTE_IPCTRL">
        <column name="ID" primaryKey="true" required="true" size="10" type="DECIMAL"/>
        <column name="TITLE_ID" size="10" type="DECIMAL"/>
        <column name="IP_START" size="100" type="VARCHAR"/>
        <column name="IP_END" size="100" type="VARCHAR"/>
        <foreign-key foreignTable="TD_CMS_VOTE_TITLE">
            <reference foreign="ID" local="TITLE_ID"/>
        </foreign-key>
    </table>
    <table name="TD_CMS_VOTE_ITEMS">
        <column name="ID" primaryKey="true" required="true" size="22" type="DECIMAL"/>
        <column name="QID" size="22" type="DECIMAL"/>
        <column name="OPTIONS" size="200" type="VARCHAR"/>
        <column default="0" name="COUNT" size="22" type="DECIMAL"/>
        <foreign-key foreignTable="TD_CMS_VOTE_QUESTIONS">
            <reference foreign="ID" local="QID"/>
        </foreign-key>
    </table>
    <table name="TD_CMS_VOTE_QUESTIONS">
        <column name="ID" primaryKey="true" required="true" size="22" type="DECIMAL"/>
        <column name="TITLE" size="200" type="VARCHAR"/>
        <column name="STYLE" size="1" type="DECIMAL"/>
        <column default="0" name="VOTECOUNT" size="22" type="DECIMAL"/>
        <column default="1" name="ACTIVE" size="1" type="DECIMAL"/>
        <column default="0" name="ISTOP" size="1" type="DECIMAL"/>
    </table>
    <table name="TD_CMS_VOTE_TIMECTRL">
        <column name="ID" primaryKey="true" required="true" size="10" type="DECIMAL"/>
        <column name="TITLE_ID" size="10" type="DECIMAL"/>
        <column name="TIME_START" type="DATE"/>
        <column name="TIME_END" type="DATE"/>
        <foreign-key foreignTable="TD_CMS_VOTE_TITLE">
            <reference foreign="ID" local="TITLE_ID"/>
        </foreign-key>
    </table>
    <table name="TD_CMS_VOTE_TITLE">
        <column name="NAME" size="200" type="VARCHAR"/>
        <column name="CONTENT" type="CLOB"/>
        <column name="ID" primaryKey="true" required="true" size="10" type="DECIMAL"/>
        <column default="1" name="SITEID" size="10" type="DECIMAL"/>
        <column name="IP_REPEAT" size="1" type="DECIMAL"/>
        <column name="TIME_GAP" size="22" type="DECIMAL"/>
        <column name="FOUNDER_ID" size="22" type="DECIMAL"/>
        <column default="0" name="ACTIVE" size="1" type="DECIMAL"/>
        <column name="SEETYPE" size="1" type="DECIMAL"/>
        <column name="CTIME" type="DATE"/>
        <column default="0" name="ISTOP" size="1" type="DECIMAL"/>
        <column name="PICPATH" size="500" type="VARCHAR"/>
        <column name="DEPART_ID" size="20" type="VARCHAR"/>
        <column default="1" name="ISLOOK" size="22" type="DECIMAL"/>
        <column default="0" name="USER_REPEAT" size="1" type="DECIMAL"/>
        <column name="USER_TIME_GAP" size="22" type="DECIMAL"/>
    </table>
    <table name="TD_CMS_VOTE_TQ">
        <column name="TITLE_ID" primaryKey="true" required="true"
            size="10" type="DECIMAL"/>
        <column name="QUESIONT_ID" primaryKey="true" required="true"
            size="10" type="DECIMAL"/>
        <foreign-key foreignTable="TD_CMS_VOTE_QUESTIONS">
            <reference foreign="ID" local="QUESIONT_ID"/>
        </foreign-key>
        <foreign-key foreignTable="TD_CMS_VOTE_TITLE">
            <reference foreign="ID" local="TITLE_ID"/>
        </foreign-key>
    </table>
   
    <table name="TL_CMS_DOC_OPER_LOG">
        <column name="ID" primaryKey="true" required="true" size="10" type="DECIMAL"/>
        <column name="USER_ID" required="true" size="22" type="DECIMAL"/>
        <column name="DOC_ID" required="true" size="22" type="DECIMAL"/>
        <column name="DOC_OPER_ID" required="true" size="22" type="DECIMAL"/>
        <column name="DOC_TRANS_ID" size="22" type="DECIMAL"/>
        <column name="OPER_TIME" required="true" type="DATE"/>
        <column name="OPER_CONTENT" size="1000" type="VARCHAR"/>
        <foreign-key foreignTable="TB_CMS_DOC_STATUS_TRANS">
            <reference foreign="ID" local="DOC_TRANS_ID"/>
        </foreign-key>
        <foreign-key foreignTable="TB_CMS_DOC_OPER">
            <reference foreign="ID" local="DOC_OPER_ID"/>
        </foreign-key>
        <foreign-key foreignTable="TD_CMS_DOCUMENT">
            <reference foreign="DOCUMENT_ID" local="DOC_ID"/>
        </foreign-key>
    </table>
    <table name="TL_CMS_SITE_FLOW_HIS">
        <column name="SITE_ID" required="true" size="10" type="DECIMAL"/>
        <column name="OLD_FLOW_ID" size="22" type="DECIMAL"/>
        <column name="NEW_FLOW_ID" required="true" size="22" type="DECIMAL"/>
        <column name="OP_USER_ID" required="true" size="22" type="DECIMAL"/>
        <column name="OP_TIME" type="DATE"/>
        <foreign-key foreignTable="TD_CMS_SITE">
            <reference foreign="SITE_ID" local="SITE_ID"/>
        </foreign-key>
        <foreign-key foreignTable="TB_CMS_FLOW">
            <reference foreign="ID" local="NEW_FLOW_ID"/>
        </foreign-key>
        <foreign-key foreignTable="TB_CMS_FLOW">
            <reference foreign="ID" local="OLD_FLOW_ID"/>
        </foreign-key>
    </table>
   
    <table name="X_TD_CMS_PUBLISHSCHEDULAR">
        <column name="SCHEDULERTYPE" size="5" type="DECIMAL"/>
        <column name="STARTTIME" type="DATE"/>
        <column name="PUBLISHTIMES" size="5" type="DECIMAL"/>
        <column name="PUBLISHINTERVAL" size="5" type="DECIMAL"/>
        <column name="ENDTIME" type="DATE"/>
        <column name="PUBLISHSCHEDULAR_ID" required="true" size="10" type="DECIMAL"/>
        <column name="SITE_ID" size="10" type="DECIMAL"/>
        <column name="DOCUMENT_ID" required="true" size="10" type="DECIMAL"/>
        <column name="CHANNEL_ID" size="10" type="DECIMAL"/>
        <foreign-key foreignTable="TD_CMS_CHANNEL">
            <reference foreign="CHANNEL_ID" local="CHANNEL_ID"/>
        </foreign-key>
    </table>
   
</database>
